script_to_pipeline/__init__.py
script_to_pipeline/__main__.py
script_to_pipeline/_internal.py
script_to_pipeline/constants.py
script_to_pipeline/entrypoint/__main__.py
script_to_pipeline/models.py
script_to_pipeline/pfs.py
script_to_pipeline/utils.py
script_to_pipeline-0.2.0a4.dist-info/entry_points.txt
script_to_pipeline-0.2.0a4.dist-info/WHEEL
script_to_pipeline-0.2.0a4.dist-info/METADATA
script_to_pipeline-0.2.0a4.dist-info/RECORD
