Metadata-Version: 2.1
Name: script-to-pipeline
Version: 0.2.0a4
Summary: Tool for converting python scripts into Pachyderm pipelines.
Author: Ben Bonenfant
Author-email: bonenfan5ben@gmail.com
Requires-Python: >=3.7,<4.0
Classifier: Programming Language :: Python :: 3
Classifier: Programming Language :: Python :: 3.7
Classifier: Programming Language :: Python :: 3.8
Classifier: Programming Language :: Python :: 3.9
